znsocket/__init__.py
znsocket/abc.py
znsocket/cli.py
znsocket/client.py
znsocket/exceptions.py
znsocket/server.py
znsocket/utils.py
znsocket/objects/__init__.py
znsocket/objects/dict_adapter.py
znsocket/objects/dict_obj.py
znsocket/objects/list_adapter.py
znsocket/objects/list_obj.py
znsocket/objects/segments_obj.py
znsocket/storages/__init__.py
znsocket/storages/memory.py
znsocket-0.3.0.dist-info/METADATA
znsocket-0.3.0.dist-info/WHEEL
znsocket-0.3.0.dist-info/entry_points.txt
znsocket-0.3.0.dist-info/licenses/LICENSE
znsocket-0.3.0.dist-info/RECORD
