Metadata-Version: 2.4
Name: znsocket
Version: 0.3.0
Summary: Python implementation of a Redis-compatible API using websockets.
Project-URL: Repository, https://github.com/zincware/ZnSocket
Project-URL: Releases, https://github.com/zincware/ZnSocket/releases
Author-email: Fabian Zills <fzills@icp.uni-stuttgart.de>
License-Expression: Apache-2.0
License-File: LICENSE
Requires-Python: >=3.10
Requires-Dist: eventlet>=0.39.0
Requires-Dist: python-socketio[client]>=5.12.1
Requires-Dist: redis>=5.2.1
Requires-Dist: sortedcontainers>=2.4.0
Requires-Dist: typer>=0.13
Requires-Dist: znjson>=0.2.6
